{
  "slug": "dharma-talk",
  "themeIds": [
    "compassion",
    "enlightenment",
    "inner-peace",
    "personal-growth"
  ],
  "related": [
    {
      "slug": "energy-compassion-and-healing",
      "rationale": "Picks up the thread of compassion and pushes it into energy healing practices."
    },
    {
      "slug": "white-tara-comes-to-oklahoma-city",
      "rationale": "Picks up the thread of compassion and bodhicitta in Oklahoma."
    },
    {
      "slug": "mothers-day-and-compassion",
      "rationale": "Picks up compassion thread from Buddhist context into family life."
    }
  ]
}